LICENSE.txt
MANIFEST.in
README.rst
setup.py
firstdown_cloud/__init__.py
firstdown_cloud/aspLog.py
firstdown_cloud/s3.py
firstdown_cloud/service_check.py
firstdown_cloud/sns.py
firstdown_cloud.egg-info/PKG-INFO
firstdown_cloud.egg-info/SOURCES.txt
firstdown_cloud.egg-info/dependency_links.txt
firstdown_cloud.egg-info/entry_points.txt
firstdown_cloud.egg-info/requires.txt
firstdown_cloud.egg-info/top_level.txt